[
    {
        "ParameterKey": "AppName",
        "ParameterValue": "AWSBilling"
    },
    {
        "ParameterKey": "Environment",
        "ParameterValue": "Dev"
    },
    {
        "ParameterKey": "CodeS3Bucket",
        "ParameterValue": "peng-176-cost-calculator-python-bucket"
    },
    {
        "ParameterKey": "CodeZipName",
        "ParameterValue": "lambda_package_123.zip"
    },
    {
        "ParameterKey": "S3SourceBucketName",
        "ParameterValue": "peng-176-cost-monitoring-lambda-source-bucket"
    },
    {
        "ParameterKey": "S3FileName",
        "ParameterValue": "version-1/config.yaml"
    }
]